Proyecto_Diseño_Logico/Datapath/RegistroUniversal.v
`timescale 1ns/1ps

module RegistroUniversal #(parameter ANCHO=8)(
	input clk, rst,
	input [1:0] Control,
	input InHaciaDerecha, //Primer bit de la suma o Ultimo bit del registro A
	input [ANCHO-1:0] ResultadoSuma,
	input [ANCHO-1:0] EntradaParalela,
	output reg [ANCHO-1:0] Salida
);

reg [ANCHO-1:0]state,next_state;	
parameter Add_regs=2'b00,Shift_regs=2'b01;
parameter Decr_P=2'b10, Load_regs=2'b11; 
//memoria
always @(posedge clk) begin
	if(!rst) state<=0;
	else state<=next_state;
end

//siguiente estado
if(ANCHO==4)
	always @(*) begin
		case(Control)
			Add_regs: next_state=state; //memoria, se mantiene el dato
			Shift_regs: next_state=state;
			Decr_P: next_state=state-1'b1;
			Load_regs: next_state=EntradaParalela;
		endcase
	end
else		
	always @(*) begin
		case(Control)
			Add_regs: next_state=ResultadoSuma; //memoria, se mantiene el dato
			Shift_regs: next_state={InHaciaDerecha,state[ANCHO-1:1]};
			Decr_P: next_state=state;
			Load_regs: next_state=EntradaParalela;
		endcase
	end

//salidas
always @(*) begin
	Salida=state;
end

endmodule

Proyecto_Diseño_Logico/Datapath/Sumador.v
`timescale 1ns/1ps

module Sumador #(parameter ANCHO=8)(
  input [ANCHO-1:0] a,
  input [ANCHO-1:0] b,
  input cin,
  input [ANCHO-1:0] Control,
  output reg [ANCHO-1:0] sum,
  output reg cout
);

  reg [ANCHO:0] sumita;
  always @(*) begin
    sumita = a + b;
        if(Control == 2'b00)
              sum = sumita[ANCHO-1:0];
        cout = sumita[ANCHO];
  end
endmodule

Proyecto_Diseño_Logico/Datapath/Datapath.v
`timescale 1ns/1ps

module Datapath #(parameter ANCHO=8) (
	input clk,Load_regs,Shift_regs,Add_regs,Decr_P,
	input [ANCHO-1:0] Multiplicando,
	input [ANCHO-1:0] Multiplicador,
	output reg [ANCHO*2:0] Producto,
    output reg Zero,Q_Cero
);
  
	wire rst;
	wire [ANCHO-1:0] OUT_SUMADOR_IN_REGA;
	wire [ANCHO-1:0] IN_REGB;
	wire [ANCHO-1:0] OUT_REGB_IN_SUMA;
	wire [ANCHO-1:0] OUT_REGA_IN_SUMA;
	wire [ANCHO-1:0] OUT_REGQ;
	wire Suma_MSB, REGA_LSB;
	wire [ANCHO-5:0] Contador;
	reg [1:0] Control;
	reg [ANCHO-5:0] PaseAControl;
  
	
	//Logica para comandos en registros
	always @(*) begin
      	PaseAControl={Add_regs,Shift_regs,Decr_P,Load_regs};
		case(PaseAControl)
			4'b1000: Control=2'b00; //Add_regs
			4'b0100: Control=2'b01; //Shift_regs
			4'b0010: Control=2'b10; //Decr_P
			4'b0001: Control=2'b11; //Load_regs
		endcase
	end
	
	
	Sumador #(.ANCHO(ANCHO)) SUMA (.a(OUT_REGA_IN_SUMA),.b(OUT_REGB_IN_SUMA),.cin(1'b0),.sum(OUT_SUMADOR_IN_REGA),.cout(Suma_MSB),.Control(Control));
		
	RegistroUniversal #(.ANCHO(ANCHO)) REGISTRO_A (
	.clk(clk),
	.rst(rst),
	.Control(Control),
	.InHaciaDerecha(Suma_MSB),
	.ResultadoSuma(OUT_SUMADOR_IN_REGA),
    .EntradaParalela(8'b00000000),
	.Salida(OUT_REGA_IN_SUMA)
);

	RegistroUniversal #(.ANCHO(ANCHO)) REGISTRO_Q (
	.clk(clk),
	.rst(rst),
	.Control(Control),
	.InHaciaDerecha(REGA_LSB),
	.ResultadoSuma(OUT_REGQ),
	.EntradaParalela(Multiplicador),
	.Salida(OUT_REGQ)
);

	RegistroUniversal #(.ANCHO(ANCHO)) REGISTRO_B (
	.clk(clk),
	.rst(rst),
	.Control(2'b11),
	.InHaciaDerecha(1'b0),
	.ResultadoSuma(1'b0),
	.EntradaParalela(Multiplicando),
	.Salida(OUT_REGB_IN_SUMA)
);

	RegistroUniversal #(.ANCHO(ANCHO-4)) REGISTRO_P (
	.clk(clk),
	.rst(rst),
	.Control(Control),
	.InHaciaDerecha(1'b0),
	.ResultadoSuma(1'b0),
	.EntradaParalela(4'b1000),
	.Salida(Contador)
);

	//Logica de salida
  	  
	always @(*) begin
		assign Producto = {Suma_MSB,OUT_REGA_IN_SUMA,OUT_REGQ};
		assign Q_Cero = OUT_REGQ[0];
      	if(Contador==4'b0000)
			Zero=1;
		else
			Zero=0;
	end
	
	//definimos el 	valor de la salida..	
	//assign Salida=	OUT_SUMADOR_IN_REG1; //copiar salida del sumador
	
endmodule

Proyecto_Diseño_Logico/Datapath/tb_Datapath.v
`timescale 1ns/1ps
module tb_Datapath;

// Definicion de las variables a utilizar
parameter ANCHO=8;
reg clk, rst;
reg Load_regs,Shift_regs,Add_regs,Decr_P;
reg [ANCHO-1:0] Multiplicador;
reg [ANCHO-1:0] Multiplicando;
wire [ANCHO*2:0] Producto;
wire Q_Cero, Zero;


// Creando una instancia del controlador
Datapath #(.ANCHO(ANCHO)) DUT(
	.clk(clk),.Load_regs(Load_regs),.Shift_regs(Shift_regs),.Add_regs(Add_regs),.Decr_P(Decr_P),
	.Multiplicando(Multiplicando),
	.Multiplicador(Multiplicador),
	.Producto(Producto),
    .Zero(Zero),.Q_Cero(Q_Cero)
);


// Generacion de graficas
initial begin
  $dumpfile("datapath.vcd");
  $dumpvars(0, tb_Datapath);
end


// Reloj de 100 MHz
initial begin
    clk = 0; // En tiempo 0
end
always begin
    #5 clk = ~clk; // Periodo de 10ns  
end


// Generar el reset
initial begin
	// El controlador esta en estado reset
    Load_regs=0;
	Shift_regs=0;
	Add_regs=0;
	Decr_P=0;

    #10
	// Controlador manda a cargar los registros
	// En este punto la salida Q0 deberìa ser 1
	Multiplicador=8'b00010111;
	Multiplicando=8'b11010111;
    Load_regs=1;
	Shift_regs=0;
	Add_regs=0;
	Decr_P=0;

    #10 
	// Controlador se encuentra en un estado en donde lee Q0
	//En este punto Q0 deberia de ser 1
    Load_regs=0;
	Shift_regs=0;
	Add_regs=0;
	Decr_P=0;

    #10
	// Si Q0 es 1, controlador manda a sumar
	// En este instante el Datapath realiza la suma
    Load_regs=0;
	Shift_regs=0;
	Add_regs=1;
	Decr_P=0;

    #10
	// El controlador ordena hacer shift
    Load_regs=0;
	Shift_regs=1;
	Add_regs=0;
	Decr_P=0;

	#10
	// El controlador ordena hacer decremento
    Load_regs=0;
	Shift_regs=0;
	Add_regs=0;
	Decr_P=1;

	#10
	// Controlador no envia ninguna orden porque està analizando la bandera Zero
    Load_regs=0;
	Shift_regs=0;
	Add_regs=0;
	Decr_P=0;

	#10
	// Aun no termina el contador. Asi que, el controlador vuelve a analizar Q0
	// En este punto, Q0 deberia de ser 1
    Load_regs=0;
	Shift_regs=0;
	Add_regs=0;
	Decr_P=0;

 	#10
	// Si Q0 es 1, controlador manda a sumar
	// En este instante el Datapath realiza la suma
    Load_regs=0;
	Shift_regs=0;
	Add_regs=1;
	Decr_P=0;

    #10
	// El controlador ordena hacer shift
	// Se valida la salida Zero
    Load_regs=0;
	Shift_regs=1;
	Add_regs=0;
	Decr_P=0;

	#10
	// El controlador ordena hacer decremento
    Load_regs=0;
	Shift_regs=0;
	Add_regs=0;
	Decr_P=1;

	#10
	// Controlador no envia ninguna orden porque està analizando la bandera Zero
    Load_regs=0;
	Shift_regs=0;
	Add_regs=0;
	Decr_P=0;


	#10
	// Aun no termina el contador. Asi que, el controlador vuelve a analizar Q0
	// En este punto, Q0 deberia de ser 1
    Load_regs=0;
	Shift_regs=0;
	Add_regs=0;
	Decr_P=0;

	$finish;

end
endmodule

Proyecto_Diseño_Logico/Datapath/datapath.vcd
$date
	Mon Nov  8 05:26:30 2021
$end
$version
	Icarus Verilog
$end
$timescale
	1ps
$end
$scope module tb_Datapath $end
$var wire 1 ! Zero $end
$var wire 1 " Q_Cero $end
$var wire 17 # Producto [16:0] $end
$var reg 1 $ Add_regs $end
$var reg 1 % Decr_P $end
$var reg 1 & Load_regs $end
$var reg 8 ' Multiplicador [7:0] $end
$var reg 8 ( Multiplicando [7:0] $end
$var reg 1 ) Shift_regs $end
$var reg 1 * clk $end
$scope module DUT $end
$var wire 1 $ Add_regs $end
$var wire 1 % Decr_P $end
$var wire 1 & Load_regs $end
$var wire 8 + Multiplicador [7:0] $end
$var wire 8 , Multiplicando [7:0] $end
$var wire 1 - REGA_LSB $end
$var wire 1 ) Shift_regs $end
$var wire 1 * clk $end
$var wire 1 . rst $end
$var wire 1 / Suma_MSB $end
$var wire 8 0 OUT_SUMADOR_IN_REGA [7:0] $end
$var wire 8 1 OUT_REGQ [7:0] $end
$var wire 8 2 OUT_REGB_IN_SUMA [7:0] $end
$var wire 8 3 OUT_REGA_IN_SUMA [7:0] $end
$var wire 4 4 Contador [3:0] $end
$var reg 2 5 Control [1:0] $end
$var reg 4 6 PaseAControl [3:0] $end
$var reg 17 7 Producto [16:0] $end
$var reg 1 " Q_Cero $end
$var reg 1 ! Zero $end
$scope module REGISTRO_A $end
$var wire 2 8 Control [1:0] $end
$var wire 8 9 EntradaParalela [7:0] $end
$var wire 1 * clk $end
$var wire 1 . rst $end
$var wire 8 : ResultadoSuma [7:0] $end
$var wire 1 / InHaciaDerecha $end
$var reg 8 ; Salida [7:0] $end
$var reg 8 < next_state [7:0] $end
$var reg 8 = state [7:0] $end
$scope begin genblk2 $end
$upscope $end
$upscope $end
$scope module REGISTRO_B $end
$var wire 2 > Control [1:0] $end
$var wire 8 ? EntradaParalela [7:0] $end
$var wire 1 @ InHaciaDerecha $end
$var wire 8 A ResultadoSuma [7:0] $end
$var wire 1 * clk $end
$var wire 1 . rst $end
$var reg 8 B Salida [7:0] $end
$var reg 8 C next_state [7:0] $end
$var reg 8 D state [7:0] $end
$scope begin genblk2 $end
$upscope $end
$upscope $end
$scope module REGISTRO_P $end
$var wire 2 E Control [1:0] $end
$var wire 4 F EntradaParalela [3:0] $end
$var wire 1 G InHaciaDerecha $end
$var wire 4 H ResultadoSuma [3:0] $end
$var wire 1 * clk $end
$var wire 1 . rst $end
$var reg 4 I Salida [3:0] $end
$var reg 4 J next_state [3:0] $end
$var reg 4 K state [3:0] $end
$scope begin genblk1 $end
$upscope $end
$upscope $end
$scope module REGISTRO_Q $end
$var wire 2 L Control [1:0] $end
$var wire 8 M EntradaParalela [7:0] $end
$var wire 1 - InHaciaDerecha $end
$var wire 1 * clk $end
$var wire 1 . rst $end
$var wire 8 N ResultadoSuma [7:0] $end
$var reg 8 O Salida [7:0] $end
$var reg 8 P next_state [7:0] $end
$var reg 8 Q state [7:0] $end
$scope begin genblk2 $end
$upscope $end
$upscope $end
$scope module SUMA $end
$var wire 8 R Control [7:0] $end
$var wire 8 S a [7:0] $end
$var wire 8 T b [7:0] $end
$var wire 1 U cin $end
$var reg 1 / cout $end
$var reg 8 V sum [7:0] $end
$var reg 9 W sumita [8:0] $end
$upscope $end
$upscope $end
$upscope $end
$enddefinitions $end
#0
$dumpvars
bx W
bx V
0U
bx T
bx S
b0xx R
bx Q
bx P
bx O
bx N
bx M
bx L
bx K
bx J
bx I
b0 H
0G
b1000 F
bx E
bx D
bx C
bx B
b0 A
0@
bx ?
b11 >
bx =
bx <
bx ;
bx :
b0 9
bx 8
bx 7
b0 6
bx 5
bx 4
bx 3
bx 2
bx 1
bx 0
x/
z.
z-
bx ,
bx +
0*
0)
bx (
bx '
0&
0%
0$
bx #
x"
x!
$end
#5000
1*
#10000
b0 <
b1000 J
b10111 P
b11 R
b11 5
b11 8
b11 E
b11 L
b1 6
b11010111 C
0*
1&
b11010111 (
b11010111 ,
b11010111 ?
b10111 '
b10111 +
b10111 M
#15000
0!
1"
b10111 #
b10111 7
0/
b11010111 W
b1000 4
b1000 I
b11010111 2
b11010111 B
b11010111 T
b10111 1
b10111 N
b10111 O
b0 3
b0 ;
b0 S
b1000 K
b11010111 D
b10111 Q
b0 =
1*
#20000
b0 6
0*
0&
#25000
1*
#30000
b11010111 0
b11010111 :
b11010111 V
b11010111 <
b0 R
b0 5
b0 8
b0 E
b0 L
b1000 6
0*
1$
#35000
b10101110 <
1/
b10101110 0
b10101110 :
b10101110 V
b110101110 W
b11010111 3
b11010111 ;
b11010111 S
b11010111 =
1*
#40000
b11101011 <
bz0001011 P
b1 R
b1 5
b1 8
b1 E
b1 L
b100 6
0*
0$
1)
#45000
b111000010 W
b11101011 3
b11101011 ;
b11101011 S
b11110101 <
bz0001011 1
bz0001011 N
bz0001011 O
bz000101 P
b11101011 =
bz0001011 Q
1*
#50000
b11101011 <
b111 J
bz0001011 P
b10 R
b10 5
b10 8
b10 E
b10 L
b10 6
0*
1%
0)
#55000
b111101011z0001011 #
b111101011z0001011 7
b111 4
b111 I
b110 J
b111 K
1*
#60000
b0 6
0*
0%
#65000
b110 4
b110 I
b101 J
b110 K
1*
#70000
0*
#75000
b101 4
b101 I
b100 J
b101 K
1*
#80000
b11000010 0
b11000010 :
b11000010 V
b11000010 <
b101 J
b0 R
b0 5
b0 8
b0 E
b0 L
b1000 6
0*
1$
#85000
b10011001 <
b10011001 0
b10011001 :
b10011001 V
b110011001 W
b11000010 3
b11000010 ;
b11000010 S
b11000010 =
1*
#90000
b11100001 <
bz000101 P
b1 R
b1 5
b1 8
b1 E
b1 L
b100 6
0*
0$
1)
#95000
b110111000 W
bz000101 1
bz000101 N
bz000101 O
bz00010 P
b11100001 3
b11100001 ;
b11100001 S
b11110000 <
bz000101 Q
b11100001 =
1*
#100000
b11100001 <
b100 J
bz000101 P
b10 R
b10 5
b10 8
b10 E
b10 L
b10 6
0*
1%
0)
#105000
b111100001zz000101 #
b111100001zz000101 7
b100 4
b100 I
b11 J
b100 K
1*
#110000
b0 6
0*
0%
#115000
b11 4
b11 I
b10 J
b11 K
1*
