Proyecto_Diseño_Logico/Multiplicador_MMP/RegistroUniversal.v
`timescale 1ns/1ps

module RegistroUniversal #(parameter ANCHO=8)(
	input clk, rst,
  	input [3:0] Control,
	input InHaciaDerecha, //Primer bit de la suma o Ultimo bit del registro A
	input [ANCHO-1:0] ResultadoSuma,
	input [ANCHO-1:0] EntradaParalela,
	output reg [ANCHO-1:0] Salida
);
reg [ANCHO-1:0]state,next_state;
parameter Memoria=4'b0000;
parameter Add_regs=4'b1000,Shift_regs=4'b0100;
parameter Decr_P=4'b0010, Load_regs=4'b0001; 
//memoria
always @(negedge clk) begin
	if(!rst) state<=0;
	else state<=next_state;
end

//siguiente estado
if(ANCHO==8) begin
	always @(*) begin
		case(Control)
          Memoria: next_state=state;
          Add_regs: next_state=ResultadoSuma; //memoria, se mantiene el dato
          Shift_regs: next_state={InHaciaDerecha,state[ANCHO-1:1]};
          Decr_P: next_state=state;
          Load_regs: next_state=EntradaParalela;
          default:next_state=state;
		endcase
	end
end
else begin	
	always @(*) begin
		case(Control)
          	Memoria:next_state=state;
        	Add_regs: next_state=state; //memoria, se mantiene el dato
            Shift_regs: next_state=state;
            Decr_P: next_state=state-1'b1;
            Load_regs: next_state=EntradaParalela;
            default:next_state=state;
        endcase
	end
end

//salidas
always @(*) begin
	Salida=state;
end
endmodule

Proyecto_Diseño_Logico/Datapath/Sumador.v
`timescale 1ns/1ps

module Sumador #(parameter ANCHO=8)(
  input [ANCHO-1:0] a,
  input [ANCHO-1:0] b,
  input cin,
  input [ANCHO-1:0] Control,
  output reg [ANCHO-1:0] sum,
  output reg cout
);

  reg [ANCHO:0] sumita;
  always @(*) begin
    sumita = a + b;
        if(Control == 2'b00)
              sum = sumita[ANCHO-1:0];
        cout = sumita[ANCHO];
  end
endmodule

Multiplicador/Datapath.v
`timescale 1ns/1ps

module Datapath #(parameter ANCHO=8) (
	input clk,Load_regs,Shift_regs,Add_regs,Decr_P,
	input [ANCHO-1:0] Multiplicando,
	input [ANCHO-1:0] Multiplicador,
	output  [ANCHO*2:0] Producto,
    output reg Zero,
  	output Q_Cero
);
  
	wire rst;
	wire [ANCHO-1:0] OUT_SUMADOR_IN_REGA;
	wire [ANCHO-1:0] IN_REGB;
	wire [ANCHO-1:0] OUT_REGB_IN_SUMA;
	wire [ANCHO-1:0] OUT_REGA_IN_SUMA;
	wire [ANCHO-1:0] OUT_REGQ;
	wire Suma_MSB;
  	wire REGA_LSB;
	wire [ANCHO-5:0] Contador;
	reg [3:0] Control;
	reg [ANCHO-5:0] PaseAControl;
	
	
	//Logica para comandos en registros
	always @(*) begin
      	Control={Add_regs,Shift_regs,Decr_P,Load_regs};
		
	end
	
	
  Sumador #(.ANCHO(ANCHO)) SUMA (.a(OUT_REGA_IN_SUMA),.b(OUT_REGB_IN_SUMA),.cin(1'b0),.sum(OUT_SUMADOR_IN_REGA),.cout(Suma_MSB),.Control(Control));
		
	RegistroUniversal #(.ANCHO(ANCHO)) REGISTRO_A (
	.clk(clk),
	.rst(rst),
	.Control(Control),
	.InHaciaDerecha(Suma_MSB),
	.ResultadoSuma(OUT_SUMADOR_IN_REGA),
      .EntradaParalela(8'b00000000),
	.Salida(OUT_REGA_IN_SUMA)
);

	RegistroUniversal #(.ANCHO(ANCHO)) REGISTRO_Q (
	.clk(clk),
	.rst(rst),
	.Control(Control),
	.InHaciaDerecha(OUT_REGA_IN_SUMA[0]),
	.ResultadoSuma(OUT_REGQ),
	.EntradaParalela(Multiplicador),
	.Salida(OUT_REGQ)
);

	RegistroUniversal #(.ANCHO(ANCHO)) REGISTRO_B (
	.clk(clk),
	.rst(rst),
      .Control(4'b0001),
      .InHaciaDerecha(1'b0),
	.ResultadoSuma(8'b00000000),
	.EntradaParalela(Multiplicando),
	.Salida(OUT_REGB_IN_SUMA)
);

	RegistroUniversal #(.ANCHO(ANCHO-4)) REGISTRO_P (
	.clk(clk),
	.rst(rst),
	.Control(Control),
	.InHaciaDerecha(1'b0),
	.ResultadoSuma(4'b0000),
	.EntradaParalela(4'b1000),
	.Salida(Contador)
);
	assign Producto={Suma_MSB,OUT_REGA_IN_SUMA,OUT_REGQ};
	assign Q_Cero = OUT_REGQ[0];
  	
	//Logica de salida
  	/*always @(*) begin
      if(Control == 4'b0010)
		Producto = {Suma_MSB,OUT_REGA_IN_SUMA,OUT_REGQ};
      else
        Producto=0;
	end 
	*/always @(*) begin
      if(Contador==4'b0000)begin
		Zero=1;
      end
      else
		Zero=0;
	end
	
	//definimos el 	valor de la salida..	
	//assign Salida=	OUT_SUMADOR_IN_REG1; //copiar salida del sumador
	
endmodule

Proyecto_Diseño_Logico/Multiplicador_MMP/Controller.v
// Code your design here
`timescale 1ns / 1ps

//Mux 8 a 1

module MuxCondiciones #(parameter SEL_BITS=3)(
    input [SEL_BITS-1:0] sel, //Bus de selección con ancho SEL_BITS (ej.: 3 bits)
    input [(2**SEL_BITS)-1:0] in_bits, //los bits de entrada: 2^SEL_BITS (ej.: 2^3=8 bits)
    output reg out //bit de salida
    );
    
    always @(*)
        out = in_bits[sel];
        
endmodule

//contador con carga

module CounterWithLoad #(parameter ANCHO = 8) (
    input clk,
    input rst,
    input LD_C, //cargar (1), contar (0)
    input [ANCHO-1:0] CuentaEntrada, //Valor para carga paralela (donde vamos a saltar)
    output reg [ANCHO-1:0] cuenta  //salida del contador
    );
    
    always @(posedge clk)
      if (!rst) //reset activo en BAJO
         cuenta <= {ANCHO{1'b0}};
      else
         if (LD_C) //si LD_C es 1 entonces cargue el valor a la entrada
            cuenta <= CuentaEntrada;
         else // sino entonces cuente hacia arriba
            cuenta <= cuenta + 1'b1;
    
endmodule

// Memoria ROM 20bits x 256

module SimpleRom  #(parameter ANCHO = 20, parameter ANCHO_DIR = 8) (
    //ANCHO: es el tamaño de las palabras almacenadas
    //ANCHO_DIR: El ancho del bus de direcciones!
    //por defecto:
    //Bus de direcciones de 8 bits, lo que genera una memoria con un Largo de 256 palabras
    //El bus de datos es de 20 bits 
    input [ANCHO_DIR-1:0]A, //dirección 
    output [ANCHO-1:0]Do //Dato de salida
    );
    reg [ANCHO-1:0] MATRIX [0:(2**ANCHO_DIR)-1];
    
    initial begin
        $readmemh("rom_content_t.mem", MATRIX); //cargar contenido de archivo de memoria (binario)
    end    
    
    assign #5 Do = MATRIX[A]; //simulando 25ns de retraso (un poco más real)
    
endmodule

//controlador microprogramado
module Controlador(
    input clk,
    input rst,
    input Start,
    input Q0,
    input Zero,
    input Condicion4,
    input Condicion5,
    input Condicion6,
    output Load_regs,
    output Shift_regs,
    output Add_regs,
    output Decr_P,
    output ready,
    output salida5,
    output salida6,
    output salida7
    );
    
    parameter ANCHO_CONTADOR = 8;//Ancho del contador y del bus de la memoria
    parameter BITS_SELECCION_SALTO = 3;//bits usados para seleccionar condiciones de salto
    parameter ANCHO_MEMORIA = ANCHO_CONTADOR+8+1+BITS_SELECCION_SALTO; //20 bits en este ejemplo
    
    
    wire [ANCHO_CONTADOR-1:0] Cuenta_Direccion_Memoria;
    wire [ANCHO_CONTADOR-1:0] Direccion_Salto;
    wire [BITS_SELECCION_SALTO-1:0] Seleccion_De_Condicion_Salto;
    wire Senal_De_Carga_Contador;
    
    wire tmp0;//para relleno, no se usa en este ejemplo
    
    CounterWithLoad #(.ANCHO(ANCHO_CONTADOR)) Uconta (
        .clk(clk),
        .rst(rst),
        .LD_C(Senal_De_Carga_Contador), //cargar (1), contar (0)
        .CuentaEntrada(Direccion_Salto), //Valor para carga paralela (donde vamos a saltar)
        .cuenta(Cuenta_Direccion_Memoria) //salida del contador
    );
    
    SimpleRom  #(.ANCHO(ANCHO_MEMORIA), .ANCHO_DIR(ANCHO_CONTADOR)) Umem (
        .A(Cuenta_Direccion_Memoria), //dirección 
        .Do({
            Direccion_Salto, //8 bits //bits 19-12
            salida7, //8 bits de salida  //bit 11
            salida6, //bit 10
            salida5, //bit 9
            ready, //bit 8
            Decr_P, //bit 7
            Add_regs, //bit 6
            Shift_regs, //bit 5
            Load_regs, //bit 4
            tmp0,// 1 bit de relleno  //bit 3
            Seleccion_De_Condicion_Salto //3 bits de selección de salto  //bits 2-0 
        }) //Dato de salida de memoria -- TOTAL: 20 bits (5 digitos en hex)
    );
    
    MuxCondiciones #(.SEL_BITS(BITS_SELECCION_SALTO)) MUX(
       .sel(Seleccion_De_Condicion_Salto), //Bus de selección 
       /*
       Para el ejemplo de 3 bits de selección de salto:
       La selección en 000 significa NO SALTO
       La selección en 111 significa SALTO INCONDICIONAL
       Cualquier otra selección corresponde a las condiciones...
       
       **RECORDAR que el contador salta si la condición es 1
         y continua contando si la condición es 0!!!
       */
       .in_bits(//8 opciones
            {1'b1,//salto incondicional
            Condicion6, //sel 6
            Condicion5, //sel 5
            Condicion4, //sel 4
            Zero, //sel 3
            Q0, //sel 2
            Start, //sel 1
            1'b0}//NO saltar //menos significativo
            ), //los bits de entrada: 2^SEL_BITS (ej.: 2^3=8 bits)
       .out(Senal_De_Carga_Contador) //bit de salida
    );
    
endmodule

Proyecto_Diseño_Logico/Multiplicador_MMP/Multiplicador.v
`timescale 1ns/1ps

// Modulo del sistema completo
module Multiplicador_KCA_MMP(
    input Start,
    input Clock,
    input Reset,
    input [7:0] Multiplicando,
	input [7:0] Multiplicador,
	output [16:0] Producto,
    output Ready);

// Declaraciòn de los cables que conectan en ambas partes
    wire Load_regs;
    wire Shift_regs;
    wire Add_regs;
    wire Decr_P;
    wire Zero;
    wire Q0;
    wire salida5;
    wire salida6;
    wire salida7;

// Usando una instancia del modulo Controller MMP
    Controlador TheController(
        .clk(Clock),
        .rst(Reset),
        .Start(Start),
        .Q0(Q0),
        .Zero(Zero),
        .Condicion4(1'b0),
        .Condicion5(1'b0),
        .Condicion6(1'b0),
        .ready(Ready),
        .Load_regs(Load_regs),
        .Shift_regs(Shift_regs),
        .Add_regs(Add_regs),
        .Decr_P(Decr_P),
        .salida5(salida5),
        .salida6(salida6),
        .salida7(salida7)
    );

// Usando una instancia del modulo Datapath
    Datapath TheDatapath(
        .clk(Clock),
        .Load_regs(Load_regs),
        .Shift_regs(Shift_regs),
        .Add_regs(Add_regs),
        .Decr_P(Decr_P),
        .Multiplicando(Multiplicando),
        .Multiplicador(Multiplicador),
        .Producto(Producto),
        .Zero(Zero),
        .Q_Cero(Q0)
    );

endmodule

Proyecto_Diseño_Logico/Multiplicador_MMP/tb_Multiplicador.v
`timescale 1ns/1ps

module tb_Multiplicador;

// Definicion de las variables a utilizar
reg Start;
reg Clock;
reg Reset;
reg [7:0] Multiplicando;
reg [7:0] Multiplicador;
wire [16:0] Producto;
wire Ready;

// Creando una instancia del sistema completo
Multiplicador_KCA_MMP DUT(
    .Clock(Clock), .Reset(Reset), .Start(Start),
    .Ready(Ready), .Multiplicando(Multiplicando),
    .Multiplicador(Multiplicador), .Producto(Producto)
);

// Generacion de graficas
initial begin
  $dumpfile("Multiplicador.vcd");
  $dumpvars(0, tb_Multiplicador);
end


// Reloj de 100 MHz
initial begin
    Clock = 0; // En tiempo 0
end
always begin
    #5 Clock = ~Clock; // Periodo de 10ns  
end


initial begin
    Reset = 0;
    Start = 0;
    Multiplicador = 8'b11010111; //215
	Multiplicando = 8'b11011111; //223

    @(negedge Clock)
    Reset = 1;
    #10
    Start = 1;
    #10 
    Start = 0;
    #1000
    Multiplicador = 8'b11000111; //199
	Multiplicando = 8'b01010101; //85
    #10
    Start = 1;
    #10 
    Start = 0;
    #1000
    $finish;
end
endmodule

Proyecto_Diseño_Logico/Multiplicador_MMP/Multiplicador.vcd
$date
	Mon Nov 15 16:06:57 2021
$end
$version
	Icarus Verilog
$end
$timescale
	1ps
$end
$scope module tb_Multiplicador $end
$var wire 1 ! Ready $end
$var wire 17 " Producto [16:0] $end
$var reg 1 # Clock $end
$var reg 8 $ Multiplicador [7:0] $end
$var reg 8 % Multiplicando [7:0] $end
$var reg 1 & Reset $end
$var reg 1 ' Start $end
$scope module DUT $end
$var wire 1 # Clock $end
$var wire 8 ( Multiplicador [7:0] $end
$var wire 8 ) Multiplicando [7:0] $end
$var wire 1 & Reset $end
$var wire 1 ' Start $end
$var wire 1 * salida7 $end
$var wire 1 + salida6 $end
$var wire 1 , salida5 $end
$var wire 1 - Zero $end
$var wire 1 . Shift_regs $end
$var wire 1 ! Ready $end
$var wire 1 / Q0 $end
$var wire 17 0 Producto [16:0] $end
$var wire 1 1 Load_regs $end
$var wire 1 2 Decr_P $end
$var wire 1 3 Add_regs $end
$scope module TheController $end
$var wire 1 4 Condicion4 $end
$var wire 1 5 Condicion5 $end
$var wire 1 6 Condicion6 $end
$var wire 1 ' Start $end
$var wire 1 # clk $end
$var wire 1 & rst $end
$var wire 1 7 tmp0 $end
$var wire 1 * salida7 $end
$var wire 1 + salida6 $end
$var wire 1 , salida5 $end
$var wire 1 ! ready $end
$var wire 1 - Zero $end
$var wire 1 . Shift_regs $end
$var wire 1 8 Senal_De_Carga_Contador $end
$var wire 3 9 Seleccion_De_Condicion_Salto [2:0] $end
$var wire 1 / Q0 $end
$var wire 1 1 Load_regs $end
$var wire 8 : Direccion_Salto [7:0] $end
$var wire 1 2 Decr_P $end
$var wire 8 ; Cuenta_Direccion_Memoria [7:0] $end
$var wire 1 3 Add_regs $end
$scope module MUX $end
$var wire 8 < in_bits [7:0] $end
$var wire 3 = sel [2:0] $end
$var reg 1 8 out $end
$upscope $end
$scope module Uconta $end
$var wire 8 > CuentaEntrada [7:0] $end
$var wire 1 8 LD_C $end
$var wire 1 # clk $end
$var wire 1 & rst $end
$var reg 8 ? cuenta [7:0] $end
$upscope $end
$scope module Umem $end
$var wire 8 @ A [7:0] $end
$var wire 20 A Do [19:0] $end
$upscope $end
$upscope $end
$scope module TheDatapath $end
$var wire 1 3 Add_regs $end
$var wire 1 2 Decr_P $end
$var wire 1 1 Load_regs $end
$var wire 8 B Multiplicador [7:0] $end
$var wire 8 C Multiplicando [7:0] $end
$var wire 1 . Shift_regs $end
$var wire 1 # clk $end
$var wire 1 D rst $end
$var wire 1 E Suma_MSB $end
$var wire 1 / Q_Cero $end
$var wire 17 F Producto [16:0] $end
$var wire 8 G OUT_SUMADOR_IN_REGA [7:0] $end
$var wire 8 H OUT_REGQ [7:0] $end
$var wire 8 I OUT_REGB_IN_SUMA [7:0] $end
$var wire 8 J OUT_REGA_IN_SUMA [7:0] $end
$var wire 4 K Contador [3:0] $end
$var reg 4 L Control [3:0] $end
$var reg 1 - Zero $end
$scope module REGISTRO_A $end
$var wire 4 M Control [3:0] $end
$var wire 8 N EntradaParalela [7:0] $end
$var wire 1 # clk $end
$var wire 1 D rst $end
$var wire 8 O ResultadoSuma [7:0] $end
$var wire 1 E InHaciaDerecha $end
$var reg 8 P Salida [7:0] $end
$var reg 8 Q next_state [7:0] $end
$var reg 8 R state [7:0] $end
$scope begin genblk1 $end
$upscope $end
$upscope $end
$scope module REGISTRO_B $end
$var wire 4 S Control [3:0] $end
$var wire 8 T EntradaParalela [7:0] $end
$var wire 1 U InHaciaDerecha $end
$var wire 8 V ResultadoSuma [7:0] $end
$var wire 1 # clk $end
$var wire 1 D rst $end
$var reg 8 W Salida [7:0] $end
$var reg 8 X next_state [7:0] $end
$var reg 8 Y state [7:0] $end
$scope begin genblk1 $end
$upscope $end
$upscope $end
$scope module REGISTRO_P $end
$var wire 4 Z Control [3:0] $end
$var wire 4 [ EntradaParalela [3:0] $end
$var wire 1 \ InHaciaDerecha $end
$var wire 4 ] ResultadoSuma [3:0] $end
$var wire 1 # clk $end
$var wire 1 D rst $end
$var reg 4 ^ Salida [3:0] $end
$var reg 4 _ next_state [3:0] $end
$var reg 4 ` state [3:0] $end
$scope begin genblk2 $end
$upscope $end
$upscope $end
$scope module REGISTRO_Q $end
$var wire 4 a Control [3:0] $end
$var wire 8 b EntradaParalela [7:0] $end
$var wire 1 c InHaciaDerecha $end
$var wire 1 # clk $end
$var wire 1 D rst $end
$var wire 8 d ResultadoSuma [7:0] $end
$var reg 8 e Salida [7:0] $end
$var reg 8 f next_state [7:0] $end
$var reg 8 g state [7:0] $end
$scope begin genblk1 $end
$upscope $end
$upscope $end
$scope module SUMA $end
$var wire 4 h Control [3:0] $end
$var wire 8 i a [7:0] $end
$var wire 8 j b [7:0] $end
$var wire 1 k cin $end
$var reg 1 E cout $end
$var reg 8 l sum [7:0] $end
$var reg 9 m sumita [8:0] $end
$upscope $end
$upscope $end
$upscope $end
$upscope $end
$enddefinitions $end
#0
$dumpvars
bx m
bx l
0k
b11011111 j
bx i
bx h
bx g
bx f
bx e
bx d
xc
b11010111 b
bx a
bx `
bx _
bx ^
b0 ]
0\
b1000 [
bx Z
b11011111 Y
b11011111 X
b11011111 W
b0 V
0U
b11011111 T
b1 S
bx R
bx Q
bx P
bx O
b0 N
bx M
bx L
bx K
bx J
b11011111 I
bx H
bx G
bx F
xE
zD
b11011111 C
b11010111 B
bx A
bx @
bx ?
bx >
bx =
b1000xx00 <
bx ;
bx :
bx 9
x8
x7
06
05
04
x3
x2
x1
bx 0
x/
x.
x-
x,
x+
x*
b11011111 )
b11010111 (
0'
0&
b11011111 %
b11010111 $
0#
bx "
x!
$end
#5000
b0 ;
b0 ?
b0 @
1#
#10000
08
b0 L
b0 M
b0 Z
b0 a
b0 h
b0 9
b0 =
07
01
0.
03
02
0!
0,
0+
0*
b0 :
b0 >
1&
b0 A
0#
#15000
b1 ;
b1 ?
b1 @
1#
#20000
18
b1 9
b1 =
b11 :
b11 >
b11000000000001 A
0#
b1000xx10 <
1'
#25000
b11 ;
b11 ?
b11 @
1#
#30000
b0 Q
b1000 _
b11010111 f
b1 L
b1 M
b1 Z
b1 a
b1 h
b0 9
b0 =
11
b0 :
b0 >
08
b10000 A
0#
b1000xx00 <
0'
#35000
b100 ;
b100 ?
b100 @
1#
#40000
b11011111 m
0c
1/
b10000100 <
0-
b0 J
b0 P
b0 i
bx0000000011010111 "
bx0000000011010111 0
bx0000000011010111 F
b11010111 H
b11010111 d
b11010111 e
b1000 K
b1000 ^
b0 R
b11010111 g
b1000 `
b0 Q
b1000 _
b11010111 f
18
b0 L
b0 M
b0 Z
b0 a
b0 h
b10 9
b10 =
01
b110 :
b110 >
b110000000000010 A
0#
#45000
b110 ;
b110 ?
b110 @
1#
#50000
b11011111 Q
b11010111 "
b11010111 0
b11010111 F
0E
b11011111 G
b11011111 O
b11011111 l
08
b1000 L
b1000 M
b1000 Z
b1000 a
b1000 h
b0 9
b0 =
13
b0 :
b0 >
b1000000 A
0#
#55000
b111 ;
b111 ?
b111 @
1#
#60000
b110111110 m
1c
b1101111111010111 "
b1101111111010111 0
b1101111111010111 F
b11011111 J
b11011111 P
b11011111 i
b11011111 R
b1101111 Q
b11101011 f
b100 L
b100 M
b100 Z
b100 a
b100 h
1.
03
b100000 A
0#
#65000
b1000 ;
b1000 ?
b1000 @
1#
#70000
b101001110 m
b11101011 H
b11101011 d
b11101011 e
b110111111101011 "
b110111111101011 0
b110111111101011 F
b1101111 J
b1101111 P
b1101111 i
b11101011 g
b1101111 R
b1101111 Q
b111 _
b11101011 f
b0 G
b0 O
b0 l
b10 L
b10 M
b10 Z
b10 a
b10 h
0.
12
b10000000 A
0#
#75000
b1001 ;
b1001 ?
b1001 @
1#
#80000
b111 K
b111 ^
b111 `
b111 _
b0 L
b0 M
b0 Z
b0 a
b0 h
b11 9
b11 =
02
b1011 :
b1011 >
b1011000000000011 A
0#
#85000
b1010 ;
b1010 ?
b1010 @
1#
#90000
18
b111 9
b111 =
b100 :
b100 >
b100000000000111 A
0#
#95000
b100 ;
b100 ?
b100 @
1#
#100000
b10 9
b10 =
b110 :
b110 >
b110000000000010 A
0#
#105000
b110 ;
b110 ?
b110 @
1#
#110000
b1001110 Q
b10110111111101011 "
b10110111111101011 0
b10110111111101011 F
1E
b1001110 G
b1001110 O
b1001110 l
08
b1000 L
b1000 M
b1000 Z
b1000 a
b1000 h
b0 9
b0 =
13
b0 :
b0 >
b1000000 A
0#
#115000
b111 ;
b111 ?
b111 @
1#
#120000
b100101101 m
0c
b10100111011101011 "
b10100111011101011 0
b10100111011101011 F
b1001110 J
b1001110 P
b1001110 i
b1001110 R
b10100111 Q
b1110101 f
b100 L
b100 M
b100 Z
b100 a
b100 h
1.
03
b100000 A
0#
#125000
b1000 ;
b1000 ?
b1000 @
1#
#130000
b110000110 m
1c
b1110101 H
b1110101 d
b1110101 e
b10100111 J
b10100111 P
b10100111 i
b1110101 g
b10100111 R
b10100111 Q
b110 _
b1110101 f
b1010011101110101 "
b1010011101110101 0
b1010011101110101 F
0E
b0 G
b0 O
b0 l
b10 L
b10 M
b10 Z
b10 a
b10 h
0.
12
b10000000 A
0#
#135000
b1001 ;
b1001 ?
b1001 @
1#
#140000
b110 K
b110 ^
b110 `
b110 _
b0 L
b0 M
b0 Z
b0 a
b0 h
b11 9
b11 =
02
b1011 :
b1011 >
b1011000000000011 A
0#
#145000
b1010 ;
b1010 ?
b1010 @
1#
#150000
18
b111 9
b111 =
b100 :
b100 >
b100000000000111 A
0#
#155000
b100 ;
b100 ?
b100 @
1#
#160000
b10 9
b10 =
b110 :
b110 >
b110000000000010 A
0#
#165000
b110 ;
b110 ?
b110 @
1#
#170000
b10000110 Q
b11010011101110101 "
b11010011101110101 0
b11010011101110101 F
1E
b10000110 G
b10000110 O
b10000110 l
08
b1000 L
b1000 M
b1000 Z
b1000 a
b1000 h
b0 9
b0 =
13
b0 :
b0 >
b1000000 A
0#
#175000
b111 ;
b111 ?
b111 @
1#
#180000
b101100101 m
0c
b11000011001110101 "
b11000011001110101 0
b11000011001110101 F
b10000110 J
b10000110 P
b10000110 i
b10000110 R
b11000011 Q
b111010 f
b100 L
b100 M
b100 Z
b100 a
b100 h
1.
03
b100000 A
0#
#185000
b1000 ;
b1000 ?
b1000 @
1#
#190000
b10000000 <
0/
b110100010 m
1c
b111010 H
b111010 d
b111010 e
b11000011 J
b11000011 P
b11000011 i
b111010 g
b11000011 R
b11000011 Q
b101 _
b111010 f
b1100001100111010 "
b1100001100111010 0
b1100001100111010 F
0E
b0 G
b0 O
b0 l
b10 L
b10 M
b10 Z
b10 a
b10 h
0.
12
b10000000 A
0#
#195000
b1001 ;
b1001 ?
b1001 @
1#
#200000
b101 K
b101 ^
b101 `
b101 _
b0 L
b0 M
b0 Z
b0 a
b0 h
b11 9
b11 =
02
b1011 :
b1011 >
b1011000000000011 A
0#
#205000
b1010 ;
b1010 ?
b1010 @
1#
#210000
18
b111 9
b111 =
b100 :
b100 >
b100000000000111 A
0#
#215000
b100 ;
b100 ?
b100 @
1#
#220000
08
b10 9
b10 =
b110 :
b110 >
b110000000000010 A
0#
#225000
b101 ;
b101 ?
b101 @
1#
#230000
18
b111 9
b111 =
b111 :
b111 >
b111000000000111 A
0#
#235000
b111 ;
b111 ?
b111 @
1#
#240000
b1100001 Q
b10011101 f
08
b100 L
b100 M
b100 Z
b100 a
b100 h
b0 9
b0 =
1.
b0 :
b0 >
b100000 A
0#
#245000
b1000 ;
b1000 ?
b1000 @
1#
#250000
b10000100 <
1/
b101000000 m
b10011101 H
b10011101 d
b10011101 e
b110000110011101 "
b110000110011101 0
b110000110011101 F
b1100001 J
b1100001 P
b1100001 i
b10011101 g
b1100001 R
b1100001 Q
b100 _
b10011101 f
b10 L
b10 M
b10 Z
b10 a
b10 h
0.
12
b10000000 A
0#
#255000
b1001 ;
b1001 ?
b1001 @
1#
#260000
b100 K
b100 ^
b100 `
b100 _
b0 L
b0 M
b0 Z
b0 a
b0 h
b11 9
b11 =
02
b1011 :
b1011 >
b1011000000000011 A
0#
#265000
b1010 ;
b1010 ?
b1010 @
1#
#270000
18
b111 9
b111 =
b100 :
b100 >
b100000000000111 A
0#
#275000
b100 ;
b100 ?
b100 @
1#
#280000
b10 9
b10 =
b110 :
b110 >
b110000000000010 A
0#
#285000
b110 ;
b110 ?
b110 @
1#
#290000
b1000000 Q
b10110000110011101 "
b10110000110011101 0
b10110000110011101 F
1E
b1000000 G
b1000000 O
b1000000 l
08
b1000 L
b1000 M
b1000 Z
b1000 a
b1000 h
b0 9
b0 =
13
b0 :
b0 >
b1000000 A
0#
#295000
b111 ;
b111 ?
b111 @
1#
#300000
b100011111 m
0c
b10100000010011101 "
b10100000010011101 0
b10100000010011101 F
b1000000 J
b1000000 P
b1000000 i
b1000000 R
b10100000 Q
b1001110 f
b100 L
b100 M
b100 Z
b100 a
b100 h
1.
03
b100000 A
0#
#305000
b1000 ;
b1000 ?
b1000 @
1#
#310000
b10000000 <
0/
b101111111 m
b1001110 H
b1001110 d
b1001110 e
b10100000 J
b10100000 P
b10100000 i
b1001110 g
b10100000 R
b10100000 Q
b11 _
b1001110 f
b1010000001001110 "
b1010000001001110 0
b1010000001001110 F
0E
b0 G
b0 O
b0 l
b10 L
b10 M
b10 Z
b10 a
b10 h
0.
12
b10000000 A
0#
#315000
b1001 ;
b1001 ?
b1001 @
1#
#320000
b11 K
b11 ^
b11 `
b11 _
b0 L
b0 M
b0 Z
b0 a
b0 h
b11 9
b11 =
02
b1011 :
b1011 >
b1011000000000011 A
0#
#325000
b1010 ;
b1010 ?
b1010 @
1#
#330000
18
b111 9
b111 =
b100 :
b100 >
b100000000000111 A
0#
#335000
b100 ;
b100 ?
b100 @
1#
#340000
08
b10 9
b10 =
b110 :
b110 >
b110000000000010 A
0#
#345000
b101 ;
b101 ?
b101 @
1#
#350000
18
b111 9
b111 =
b111 :
b111 >
b111000000000111 A
0#
#355000
b111 ;
b111 ?
b111 @
1#
#360000
b1010000 Q
b100111 f
08
b100 L
b100 M
b100 Z
b100 a
b100 h
b0 9
b0 =
1.
b0 :
b0 >
b100000 A
0#
#365000
b1000 ;
b1000 ?
b1000 @
1#
#370000
b10000100 <
1/
b100101111 m
b100111 H
b100111 d
b100111 e
b101000000100111 "
b101000000100111 0
b101000000100111 F
b1010000 J
b1010000 P
b1010000 i
b100111 g
b1010000 R
b1010000 Q
b10 _
b100111 f
b10 L
b10 M
b10 Z
b10 a
b10 h
0.
12
b10000000 A
0#
#375000
b1001 ;
b1001 ?
b1001 @
1#
#380000
b10 K
b10 ^
b10 `
b10 _
b0 L
b0 M
b0 Z
b0 a
b0 h
b11 9
b11 =
02
b1011 :
b1011 >
b1011000000000011 A
0#
#385000
b1010 ;
b1010 ?
b1010 @
1#
#390000
18
b111 9
b111 =
b100 :
b100 >
b100000000000111 A
0#
#395000
b100 ;
b100 ?
b100 @
1#
#400000
b10 9
b10 =
b110 :
b110 >
b110000000000010 A
0#
#405000
b110 ;
b110 ?
b110 @
1#
#410000
b101111 Q
b10101000000100111 "
b10101000000100111 0
b10101000000100111 F
1E
b101111 G
b101111 O
b101111 l
08
b1000 L
b1000 M
b1000 Z
b1000 a
b1000 h
b0 9
b0 =
13
b0 :
b0 >
b1000000 A
0#
#415000
b111 ;
b111 ?
b111 @
1#
#420000
b100001110 m
1c
b10010111100100111 "
b10010111100100111 0
b10010111100100111 F
b101111 J
b101111 P
b101111 i
b101111 R
b10010111 Q
b10010011 f
b100 L
b100 M
b100 Z
b100 a
b100 h
1.
03
b100000 A
0#
#425000
b1000 ;
b1000 ?
b1000 @
1#
#430000
b101110110 m
b10010011 H
b10010011 d
b10010011 e
b10010111 J
b10010111 P
b10010111 i
b10010011 g
b10010111 R
b10010111 Q
b1 _
b10010011 f
b1001011110010011 "
b1001011110010011 0
b1001011110010011 F
0E
b0 G
b0 O
b0 l
b10 L
b10 M
b10 Z
b10 a
b10 h
0.
12
b10000000 A
0#
#435000
b1001 ;
b1001 ?
b1001 @
1#
#440000
b1 K
b1 ^
b1 `
b1 _
b0 L
b0 M
b0 Z
b0 a
b0 h
b11 9
b11 =
02
b1011 :
b1011 >
b1011000000000011 A
0#
#445000
b1010 ;
b1010 ?
b1010 @
1#
#450000
18
b111 9
b111 =
b100 :
b100 >
b100000000000111 A
0#
#455000
b100 ;
b100 ?
b100 @
1#
#460000
b10 9
b10 =
b110 :
b110 >
b110000000000010 A
0#
#465000
b110 ;
b110 ?
b110 @
1#
#470000
b1110110 Q
b11001011110010011 "
b11001011110010011 0
b11001011110010011 F
1E
b1110110 G
b1110110 O
b1110110 l
08
b1000 L
b1000 M
b1000 Z
b1000 a
b1000 h
b0 9
b0 =
13
b0 :
b0 >
b1000000 A
0#
#475000
b111 ;
b111 ?
b111 @
1#
#480000
b101010101 m
0c
b10111011010010011 "
b10111011010010011 0
b10111011010010011 F
b1110110 J
b1110110 P
b1110110 i
b1110110 R
b10111011 Q
b1001001 f
b100 L
b100 M
b100 Z
b100 a
b100 h
1.
03
b100000 A
0#
#485000
b1000 ;
b1000 ?
b1000 @
1#
#490000
b110011010 m
1c
b1001001 H
b1001001 d
b1001001 e
b10111011 J
b10111011 P
b10111011 i
b1001001 g
b10111011 R
b10111011 Q
b0 _
b1001001 f
b1011101101001001 "
b1011101101001001 0
b1011101101001001 F
0E
b0 G
b0 O
b0 l
b10 L
b10 M
b10 Z
b10 a
b10 h
0.
12
b10000000 A
0#
#495000
b1001 ;
b1001 ?
b1001 @
1#
#500000
18
b10001100 <
1-
b0 K
b0 ^
b0 `
b0 _
b0 L
b0 M
b0 Z
b0 a
b0 h
b11 9
b11 =
02
b1011 :
b1011 >
b1011000000000011 A
0#
#505000
b1011 ;
b1011 ?
b1011 @
1#
#510000
b111 9
b111 =
1!
b0 :
b0 >
b100000111 A
0#
#515000
b0 ;
b0 ?
b0 @
1#
#520000
08
b0 9
b0 =
0!
b0 A
0#
#525000
b1 ;
b1 ?
b1 @
1#
#530000
b1 9
b1 =
b11 :
b11 >
b11000000000001 A
0#
#535000
b10 ;
b10 ?
b10 @
1#
#540000
18
b111 9
b111 =
b0 :
b0 >
b111 A
0#
