Proyecto_Diseño_Logico/Datapath/RegistroUniversal.v
`timescale 1ns/1ps

module RegistroUniversal #(parameter ANCHO=8)(
	input clk, rst,
	input [1:0] Control,
	input InHaciaDerecha, //Primer bit de la suma o Ultimo bit del registro A
	input [ANCHO-1:0] ResultadoSuma,
	input [ANCHO-1:0] EntradaParalela,
	output reg [ANCHO-1:0] Salida
);

reg [ANCHO-1:0]state,next_state;	
parameter Add_regs=2'b00,Shift_regs=2'b01;
parameter Decr_P=2'b10, Load_regs=2'b11; 
//memoria
always @(posedge clk) begin
	if(!rst) state<=0;
	else state<=next_state;
end

//siguiente estado
if(ANCHO==4)
	always @(*) begin
		case(Control)
			Add_regs: next_state=state; //memoria, se mantiene el dato
			Shift_regs: next_state=state;
			Decr_P: next_state=state-1'b1;
			Load_regs: next_state=EntradaParalela;
		endcase
	end
else		
	always @(*) begin
		case(Control)
			Add_regs: next_state=ResultadoSuma; //memoria, se mantiene el dato
			Shift_regs: next_state={InHaciaDerecha,state[ANCHO-1:1]};
			Decr_P: next_state=state;
			Load_regs: next_state=EntradaParalela;
		endcase
	end

//salidas
always @(*) begin
	Salida=state;
end

endmodule

Proyecto_Diseño_Logico/Datapath/Sumador.v
`timescale 1ns/1ps

module Sumador #(parameter ANCHO=8)(
  input [ANCHO-1:0] a,
  input [ANCHO-1:0] b,
  input cin,
  input [ANCHO-1:0] Control,
  output reg [ANCHO-1:0] sum,
  output reg cout
);

  reg [ANCHO:0] sumita;
  always @(*) begin
    sumita = a + b;
        if(Control == 2'b00)
              sum = sumita[ANCHO-1:0];
        cout = sumita[ANCHO];
  end
endmodule

Proyecto_Diseño_Logico/Datapath/Datapath.v
`timescale 1ns/1ps

module Datapath #(parameter ANCHO=8) (
	input clk,Load_regs,Shift_regs,Add_regs,Decr_P,
	input [ANCHO-1:0] Multiplicando,
	input [ANCHO-1:0] Multiplicador,
	output reg [ANCHO*2:0] Producto,
    output reg Zero,Q_Cero
);
  
	wire rst;
	wire [ANCHO-1:0] OUT_SUMADOR_IN_REGA;
	wire [ANCHO-1:0] IN_REGB;
	wire [ANCHO-1:0] OUT_REGB_IN_SUMA;
	wire [ANCHO-1:0] OUT_REGA_IN_SUMA;
	wire [ANCHO-1:0] OUT_REGQ;
	wire Suma_MSB, REGA_LSB;
	wire [ANCHO-5:0] Contador;
	reg [1:0] Control;
	reg [ANCHO-5:0] PaseAControl;
  
	
	//Logica para comandos en registros
	always @(*) begin
      	PaseAControl={Add_regs,Shift_regs,Decr_P,Load_regs};
		case(PaseAControl)
			4'b1000: Control=2'b00; //Add_regs
			4'b0100: Control=2'b01; //Shift_regs
			4'b0010: Control=2'b10; //Decr_P
			4'b0001: Control=2'b11; //Load_regs
		endcase
	end
	
	
	Sumador #(.ANCHO(ANCHO)) SUMA (.a(OUT_REGA_IN_SUMA),.b(OUT_REGB_IN_SUMA),.cin(1'b0),.sum(OUT_SUMADOR_IN_REGA),.cout(Suma_MSB),.Control(Control));
		
	RegistroUniversal #(.ANCHO(ANCHO)) REGISTRO_A (
	.clk(clk),
	.rst(rst),
	.Control(Control),
	.InHaciaDerecha(Suma_MSB),
	.ResultadoSuma(OUT_SUMADOR_IN_REGA),
    .EntradaParalela(8'b00000000),
	.Salida(OUT_REGA_IN_SUMA)
);

	RegistroUniversal #(.ANCHO(ANCHO)) REGISTRO_Q (
	.clk(clk),
	.rst(rst),
	.Control(Control),
	.InHaciaDerecha(REGA_LSB),
	.ResultadoSuma(OUT_REGQ),
	.EntradaParalela(Multiplicador),
	.Salida(OUT_REGQ)
);

	RegistroUniversal #(.ANCHO(ANCHO)) REGISTRO_B (
	.clk(clk),
	.rst(rst),
	.Control(2'b11),
	.InHaciaDerecha(1'b0),
	.ResultadoSuma(1'b0),
	.EntradaParalela(Multiplicando),
	.Salida(OUT_REGB_IN_SUMA)
);

	RegistroUniversal #(.ANCHO(ANCHO-4)) REGISTRO_P (
	.clk(clk),
	.rst(rst),
	.Control(Control),
	.InHaciaDerecha(1'b0),
	.ResultadoSuma(1'b0),
	.EntradaParalela(4'b1000),
	.Salida(Contador)
);

	//Logica de salida
  	  
	always @(*) begin
		assign Producto = {Suma_MSB,OUT_REGA_IN_SUMA,OUT_REGQ};
		assign Q_Cero = OUT_REGQ[0];
      	if(Contador==4'b0000)
			Zero=1;
		else
			Zero=0;
	end
	
	//definimos el 	valor de la salida..	
	//assign Salida=	OUT_SUMADOR_IN_REG1; //copiar salida del sumador
	
endmodule

Proyecto_Diseño_Logico/Multiplicador/Controller.v
// Modulo para el controlador del proyecto del curso de Diseño Logico
`timescale 1ns/1ps

module Controller(
    input Clock, Reset, Start, Q0, Zero,
    output reg Ready, Load_regs, Shift_regs, Add_regs, Decr_P
);


// Variables de estados
reg [2:0] Current_State, Next_State;


// Definicion de los estados posiblesç
parameter SLEEP = 3'b000, LOAD_DATA = 3'b001, Q0_ONE = 3'b010, ADD = 3'b011, SHIFT = 3'b100, DECR = 3'b101, ZERO = 3'b110, READY = 3'b111;


// Logica de memoria
always @ (posedge Clock) begin
    if(!Reset) Current_State <= SLEEP;
    else Current_State <= Next_State;
end


// Logica de siguiente estado
always @(*) begin
    case (Current_State)

        SLEEP: begin
          if(Start == 1) Next_State = LOAD_DATA;
        end

        LOAD_DATA: begin
          Next_State = Q0_ONE;
        end

        Q0_ONE: begin
          if(Q0 == 1) Next_State = ADD;
          else Next_State = SHIFT;
        end

        ADD: begin
          Next_State = SHIFT;
        end

        SHIFT: begin
          Next_State = DECR;
        end

        DECR: begin
          Next_State = ZERO;
        end

        ZERO: begin
          if(Zero == 1) Next_State = READY;
          else Next_State = Q0_ONE;
        end

        READY: begin
          Next_State = SLEEP;
        end

        default: begin
          Next_State = SLEEP;
        end
    endcase    
end

// Logica de salida
always @(*) begin
    // Evitar latches
    Load_regs = 0;
    Shift_regs = 0;
    Add_regs = 0;
    Decr_P = 0;
    Ready = 0;

    case (Current_State)

        LOAD_DATA: begin
          Load_regs = 1;
          Ready = 0;
        end

        ADD: begin
            Add_regs = 1;
        end

        SHIFT: begin
            Shift_regs = 1;
        end

        DECR: begin
            Decr_P = 1;
        end

        READY: begin
            Ready = 1;
        end

    endcase     
end
endmodule

Proyecto_Diseño_Logico/Multiplicador/sistema.v
`timescale 1ns/1ps

// Modulo del sistema completo
// Controlador + Ruta de datos
module Sistema(
    input Start,
    input Clock,
    input Reset,
    input [7:0] Multiplicando,
	input [7:0] Multiplicador,
	output [16:0] Producto,
    output Ready );

// Declaraciòn de los cables que conectan ambos modulos
    wire Load_regs;
    wire Shift_regs;
    wire Add_regs;
    wire Decr_P;
    wire Zero;
    wire Q0;

// Usando una instancia del modulo Controller
    Controller TheController(
        .Clock(Clock),
        .Reset(Reset),
        .Start(Start),
        .Q0(Q0),
        .Zero(Zero),
        .Ready(Ready),
        .Load_regs(Load_regs),
        .Shift_regs(Shift_regs),
        .Add_regs(Add_regs),
        .Decr_P(Decr_P)
    );

// Usando una instancia del modulo Datapath
    Datapath TheDatapath(
        .clk(Clock),
        .Load_regs(Load_regs),
        .Shift_regs(Shift_regs),
        .Add_regs(Add_regs),
        .Decr_P(Decr_P),
        .Multiplicando(Multiplicando),
        .Multiplicador(Multiplicador),
        .Producto(Producto),
        .Zero(Zero),
        .Q_Cero(Q0)
    );


endmodule

Proyecto_Diseño_Logico/Multiplicador/tb_sistema.v
`timescale 1ns/1ps

module tb_sistema;

// Definicion de las variables a utilizar
reg Start;
reg Clock;
reg Reset;
reg [7:0] Multiplicando;
reg [7:0] Multiplicador;
wire [16:0] Producto;
wire Ready;

// Creando una instancia del controlador
Sistema DUT(
    .Clock(Clock), .Reset(Reset), .Start(Start),
    .Ready(Ready), .Multiplicando(Multiplicando),
    .Multiplicador(Multiplicador), .Producto(Producto)
);


// Generacion de graficas
initial begin
  $dumpfile("sistema.vcd");
  $dumpvars(0, tb_sistema);
end


// Reloj de 100 MHz
initial begin
    Clock = 0; // En tiempo 0
end
always begin
    #5 Clock = ~Clock; // Periodo de 10ns  
end


// Generar el reset
initial begin
    // En tiempo 0 se inicializan los datos
    Reset = 0;
    Start = 0;
    Multiplicador = 8'b00010111;
	Multiplicando = 8'b11010111;

    @(negedge Clock)
    // Se quita el Reset y se enciende el sistema
    Reset = 1;
    Start = 1;
    #15
    Start = 0;
    #200
    $finish;
end
endmodule

Proyecto_Diseño_Logico/Multiplicador/sistema.vcd
$date
	Mon Nov  8 05:45:28 2021
$end
$version
	Icarus Verilog
$end
$timescale
	1ps
$end
$scope module tb_sistema $end
$var wire 1 ! Ready $end
$var wire 17 " Producto [16:0] $end
$var reg 1 # Clock $end
$var reg 8 $ Multiplicador [7:0] $end
$var reg 8 % Multiplicando [7:0] $end
$var reg 1 & Reset $end
$var reg 1 ' Start $end
$scope module DUT $end
$var wire 1 # Clock $end
$var wire 8 ( Multiplicador [7:0] $end
$var wire 8 ) Multiplicando [7:0] $end
$var wire 1 & Reset $end
$var wire 1 ' Start $end
$var wire 1 * Zero $end
$var wire 1 + Shift_regs $end
$var wire 1 ! Ready $end
$var wire 1 , Q0 $end
$var wire 17 - Producto [16:0] $end
$var wire 1 . Load_regs $end
$var wire 1 / Decr_P $end
$var wire 1 0 Add_regs $end
$scope module TheController $end
$var wire 1 # Clock $end
$var wire 1 & Reset $end
$var wire 1 ' Start $end
$var wire 1 * Zero $end
$var wire 1 , Q0 $end
$var reg 1 0 Add_regs $end
$var reg 3 1 Current_State [2:0] $end
$var reg 1 / Decr_P $end
$var reg 1 . Load_regs $end
$var reg 3 2 Next_State [2:0] $end
$var reg 1 ! Ready $end
$var reg 1 + Shift_regs $end
$upscope $end
$scope module TheDatapath $end
$var wire 1 0 Add_regs $end
$var wire 1 / Decr_P $end
$var wire 1 . Load_regs $end
$var wire 8 3 Multiplicador [7:0] $end
$var wire 8 4 Multiplicando [7:0] $end
$var wire 1 5 REGA_LSB $end
$var wire 1 + Shift_regs $end
$var wire 1 # clk $end
$var wire 1 6 rst $end
$var wire 1 7 Suma_MSB $end
$var wire 8 8 OUT_SUMADOR_IN_REGA [7:0] $end
$var wire 8 9 OUT_REGQ [7:0] $end
$var wire 8 : OUT_REGB_IN_SUMA [7:0] $end
$var wire 8 ; OUT_REGA_IN_SUMA [7:0] $end
$var wire 4 < Contador [3:0] $end
$var reg 2 = Control [1:0] $end
$var reg 4 > PaseAControl [3:0] $end
$var reg 17 ? Producto [16:0] $end
$var reg 1 , Q_Cero $end
$var reg 1 * Zero $end
$scope module REGISTRO_A $end
$var wire 2 @ Control [1:0] $end
$var wire 8 A EntradaParalela [7:0] $end
$var wire 1 # clk $end
$var wire 1 6 rst $end
$var wire 8 B ResultadoSuma [7:0] $end
$var wire 1 7 InHaciaDerecha $end
$var reg 8 C Salida [7:0] $end
$var reg 8 D next_state [7:0] $end
$var reg 8 E state [7:0] $end
$scope begin genblk2 $end
$upscope $end
$upscope $end
$scope module REGISTRO_B $end
$var wire 2 F Control [1:0] $end
$var wire 8 G EntradaParalela [7:0] $end
$var wire 1 H InHaciaDerecha $end
$var wire 8 I ResultadoSuma [7:0] $end
$var wire 1 # clk $end
$var wire 1 6 rst $end
$var reg 8 J Salida [7:0] $end
$var reg 8 K next_state [7:0] $end
$var reg 8 L state [7:0] $end
$scope begin genblk2 $end
$upscope $end
$upscope $end
$scope module REGISTRO_P $end
$var wire 2 M Control [1:0] $end
$var wire 4 N EntradaParalela [3:0] $end
$var wire 1 O InHaciaDerecha $end
$var wire 4 P ResultadoSuma [3:0] $end
$var wire 1 # clk $end
$var wire 1 6 rst $end
$var reg 4 Q Salida [3:0] $end
$var reg 4 R next_state [3:0] $end
$var reg 4 S state [3:0] $end
$scope begin genblk1 $end
$upscope $end
$upscope $end
$scope module REGISTRO_Q $end
$var wire 2 T Control [1:0] $end
$var wire 8 U EntradaParalela [7:0] $end
$var wire 1 5 InHaciaDerecha $end
$var wire 1 # clk $end
$var wire 1 6 rst $end
$var wire 8 V ResultadoSuma [7:0] $end
$var reg 8 W Salida [7:0] $end
$var reg 8 X next_state [7:0] $end
$var reg 8 Y state [7:0] $end
$scope begin genblk2 $end
$upscope $end
$upscope $end
$scope module SUMA $end
$var wire 8 Z Control [7:0] $end
$var wire 8 [ a [7:0] $end
$var wire 8 \ b [7:0] $end
$var wire 1 ] cin $end
$var reg 1 7 cout $end
$var reg 8 ^ sum [7:0] $end
$var reg 9 _ sumita [8:0] $end
$upscope $end
$upscope $end
$upscope $end
$upscope $end
$enddefinitions $end
#0
$dumpvars
bx _
bx ^
0]
bx \
bx [
b0xx Z
bx Y
bx X
bx W
bx V
b10111 U
bx T
bx S
bx R
bx Q
b0 P
0O
b1000 N
bx M
bx L
b11010111 K
bx J
b0 I
0H
b11010111 G
b11 F
bx E
bx D
bx C
bx B
b0 A
bx @
bx ?
bx >
bx =
bx <
bx ;
bx :
bx 9
bx 8
x7
z6
z5
b11010111 4
b10111 3
b0 2
bx 1
x0
x/
x.
bx -
x,
x+
x*
b11010111 )
b10111 (
0'
0&
b11010111 %
b10111 $
0#
bx "
x!
$end
#5000
b0 >
0!
0/
00
0+
0.
b11010111 :
b11010111 J
b11010111 \
b0 1
b11010111 L
1#
#10000
b1 2
1'
1&
0#
#15000
b0 D
b1000 R
b10111 X
b11 Z
b11 =
b11 @
b11 M
b11 T
b1 >
1.
b10 2
b1 1
1#
#20000
0#
#25000
b0 >
07
b11010111 _
0*
1,
bx0000000000010111 "
bx0000000000010111 -
bx0000000000010111 ?
0.
b11 2
b0 ;
b0 C
b0 [
b10111 9
b10111 V
b10111 W
b1000 <
b1000 Q
b10 1
b0 E
b10111 Y
b1000 S
1#
0'
#30000
0#
#35000
b11010111 8
b11010111 B
b11010111 ^
b11010111 D
b0 Z
b0 =
b0 @
b0 M
b0 T
b1000 >
10
b100 2
b11 1
1#
#40000
0#
#45000
bz0001011 X
b11101011 D
b1 Z
b1 =
b1 @
b1 M
b1 T
b100 >
17
b10101110 8
b10101110 B
b10101110 ^
b110101110 _
1+
00
b101 2
b11010111 ;
b11010111 C
b11010111 [
b100 1
b11010111 E
1#
#50000
0#
#55000
b111 R
b111000010 _
b10 Z
b10 =
b10 @
b10 M
b10 T
b10 >
bz0001011 9
bz0001011 V
bz0001011 W
bz0001011 X
b11101011 ;
b11101011 C
b11101011 [
b11101011 D
1/
0+
b110 2
bz0001011 Y
b11101011 E
b101 1
1#
#60000
0#
#65000
b0 >
b111101011z0001011 "
b111101011z0001011 -
b111101011z0001011 ?
0/
b10 2
b111 <
b111 Q
b110 R
b110 1
b111 S
1#
#70000
0#
#75000
b110 <
b110 Q
b101 R
b11 2
b110 S
b10 1
1#
#80000
0#
#85000
b11000010 8
b11000010 B
b11000010 ^
b11000010 D
b0 Z
b0 =
b0 @
b0 M
b0 T
b1000 >
10
b100 2
b101 <
b101 Q
b101 R
b11 1
b101 S
1#
#90000
0#
#95000
b11100001 D
bz000101 X
b110011001 _
b1 Z
b1 =
b1 @
b1 M
b1 T
b100 >
b11000010 ;
b11000010 C
b11000010 [
1+
00
b101 2
b11000010 E
b100 1
1#
#100000
0#
#105000
b100 R
b10 Z
b10 =
b10 @
b10 M
b10 T
b10 >
b110111000 _
1/
0+
b110 2
b11100001 ;
b11100001 C
b11100001 [
b11100001 D
bz000101 9
bz000101 V
bz000101 W
bz000101 X
b101 1
b11100001 E
bz000101 Y
1#
#110000
0#
#115000
b111100001zz000101 "
b111100001zz000101 -
b111100001zz000101 ?
b0 >
b100 <
b100 Q
b11 R
0/
b10 2
b100 S
b110 1
1#
#120000
0#
#125000
b11 2
b11 <
b11 Q
b10 R
b10 1
b11 S
1#
#130000
0#
#135000
b10111000 8
b10111000 B
b10111000 ^
b10111000 D
b0 Z
b0 =
b0 @
b0 M
b0 T
b1000 >
b10 <
b10 Q
b10 R
10
b100 2
b10 S
b11 1
1#
#140000
0#
#145000
bz00010 X
b11011100 D
b1 Z
b1 =
b1 @
b1 M
b1 T
b100 >
b10001111 8
b10001111 B
b10001111 ^
b110001111 _
1+
00
b101 2
b10111000 ;
b10111000 C
b10111000 [
b100 1
b10111000 E
1#
#150000
0#
#155000
b1 R
b110110011 _
b10 Z
b10 =
b10 @
b10 M
b10 T
b10 >
bz00010 9
bz00010 V
bz00010 W
bz00010 X
b11011100 ;
b11011100 C
b11011100 [
b11011100 D
1/
0+
b110 2
bz00010 Y
b11011100 E
b101 1
1#
#160000
0#
#165000
b0 >
0,
b111011100zzz00010 "
b111011100zzz00010 -
b111011100zzz00010 ?
0/
b10 2
b1 <
b1 Q
b0 R
b110 1
b1 S
1#
#170000
0#
#175000
1*
b0 <
b0 Q
b1111 R
b100 2
b0 S
b10 1
1#
#180000
0#
#185000
b11101110 D
bz0001 X
b1 Z
b1 =
b1 @
b1 M
b1 T
b100 >
0*
1+
b101 2
b1111 <
b1111 Q
b1111 R
b100 1
b1111 S
1#
#190000
0#
#195000
b1110 R
b111000101 _
b10 Z
b10 =
b10 @
b10 M
b10 T
b10 >
bz0001 9
bz0001 V
bz0001 W
bz0001 X
b11101110 ;
b11101110 C
b11101110 [
b11101110 D
1/
0+
b110 2
bz0001 Y
b11101110 E
b101 1
1#
#200000
0#
#205000
b0 >
1,
b111101110zzzz0001 "
b111101110zzzz0001 -
b111101110zzzz0001 ?
0/
b10 2
b1110 <
b1110 Q
b1101 R
b110 1
b1110 S
1#
#210000
0#
#215000
b1101 <
b1101 Q
b1100 R
b11 2
b1101 S
b10 1
1#
#220000
0#
#225000
b11000101 8
b11000101 B
b11000101 ^
b11000101 D
b0 Z
b0 =
b0 @
b0 M
b0 T
b1000 >
10
b100 2
b1100 <
b1100 Q
b1100 R
b11 1
b1100 S
1#
